setup.py
change_build.egg-info/PKG-INFO
change_build.egg-info/SOURCES.txt
change_build.egg-info/dependency_links.txt
change_build.egg-info/entry_points.txt
change_build.egg-info/top_level.txt
changebuild/Build.py
changebuild/__init__.py